the_spymaster_api/__init__.py
the_spymaster_api/client.py
the_spymaster_api/client_classic.py
the_spymaster_api/client_duet.py
the_spymaster_api/client_mini.py
the_spymaster_api/py.typed
the_spymaster_api/structs/__init__.py
the_spymaster_api/structs/abstract/__init__.py
the_spymaster_api/structs/abstract/responses.py
the_spymaster_api/structs/classic/__init__.py
the_spymaster_api/structs/classic/requests.py
the_spymaster_api/structs/classic/responses.py
the_spymaster_api/structs/duet/__init__.py
the_spymaster_api/structs/duet/requests.py
the_spymaster_api/structs/duet/responses.py
the_spymaster_api/structs/errors.py
the_spymaster_api/structs/mini/__init__.py
the_spymaster_api/structs/mini/requests.py
the_spymaster_api/structs/mini/responses.py
the_spymaster_api/structs/requests.py
the_spymaster_api/structs/responses.py
the_spymaster_api-3.2.1.dist-info/METADATA
the_spymaster_api-3.2.1.dist-info/WHEEL
the_spymaster_api-3.2.1.dist-info/RECORD
